Metadata-Version: 2.4
Name: adafruit-circuitpython-stmpe610
Version: 1.3.20
Summary: CircuitPython library for STMPE610 Resistive Touch Screen Controller.
Author-email: Adafruit Industries <circuitpython@adafruit.com>
License: MIT
Project-URL: Homepage, https://github.com/adafruit/Adafruit_CircuitPython_STMPE610
Keywords: adafruit,stmpe610,resistive,touch,screen,controllerhardware,micropython,circuitpython
Classifier: Intended Audience :: Developers
Classifier: Topic :: Software Development :: Libraries
Classifier: Topic :: Software Development :: Embedded Systems
Classifier: Topic :: System :: Hardware
Classifier: License :: OSI Approved :: MIT License
Classifier: Programming Language :: Python :: 3
License-File: LICENSE
Requires-Dist: Adafruit-Blinka
Provides-Extra: optional
Dynamic: license-file
